breeze_chms_api/__init__.py
breeze_chms_api/breeze.py
breeze_chms_api/profile_helper.py
breeze_chms_api-1.4.4.3.dist-info/LICENSE
breeze_chms_api-1.4.4.3.dist-info/METADATA
breeze_chms_api-1.4.4.3.dist-info/WHEEL
breeze_chms_api-1.4.4.3.dist-info/top_level.txt
breeze_chms_api-1.4.4.3.dist-info/RECORD
