Metadata-Version: 2.1
Name: breeze-chms-api
Version: 1.4.4.3
Summary: Python interface to BreezeChMS REST API.
Author-email: "David A. Willcox" <daw30410@yahoo.com>
License: Apache License
Project-URL: Homepage, https://github.com/dawillcox/pyBreezeChMS
Project-URL: Bug Tracker, https://github.com/dawillcox/pyBreezeChMS/issues
Project-URL: README, https://github.com/dawillcox/pyBreezeChMS/blob/master/README.md
Project-URL: DOCUMENTATION, https://github.com/dawillcox/pyBreezeChMS/blob/master/DOCUMENTATION.md
Project-URL: Changelog, https://github.com/dawillcox/pyBreezeChMS/blob/master/CHANGELOG.md
Project-URL: REPOSITORY, https://github.com/dawillcox/pyBreezeChMS.git
Classifier: Programming Language :: Python :: 3
Classifier: License :: OSI Approved :: Apache Software License
Classifier: Operating System :: OS Independent
Classifier: Intended Audience :: Developers
Classifier: Natural Language :: English
Requires-Python: >=3.7
License-File: LICENSE
Requires-Dist: combine-settings >=1.1.0
Requires-Dist: requests >=1.1.0
